pulumiverse_unifi/__init__.py
pulumiverse_unifi/_inputs.py
pulumiverse_unifi/_utilities.py
pulumiverse_unifi/account.py
pulumiverse_unifi/device.py
pulumiverse_unifi/dynamic_dns.py
pulumiverse_unifi/get_account.py
pulumiverse_unifi/get_ap_group.py
pulumiverse_unifi/get_network.py
pulumiverse_unifi/get_radius_profile.py
pulumiverse_unifi/network.py
pulumiverse_unifi/outputs.py
pulumiverse_unifi/provider.py
pulumiverse_unifi/pulumi-plugin.json
pulumiverse_unifi/py.typed
pulumiverse_unifi/radius_profile.py
pulumiverse_unifi/site.py
pulumiverse_unifi/static_route.py
pulumiverse_unifi/wlan.py
pulumiverse_unifi/config/__init__.py
pulumiverse_unifi/config/__init__.pyi
pulumiverse_unifi/config/vars.py
pulumiverse_unifi/firewall/__init__.py
pulumiverse_unifi/firewall/group.py
pulumiverse_unifi/firewall/rule.py
pulumiverse_unifi/iam/__init__.py
pulumiverse_unifi/iam/get_group.py
pulumiverse_unifi/iam/get_user.py
pulumiverse_unifi/iam/group.py
pulumiverse_unifi/iam/user.py
pulumiverse_unifi/port/__init__.py
pulumiverse_unifi/port/forward.py
pulumiverse_unifi/port/get_profile.py
pulumiverse_unifi/port/profile.py
pulumiverse_unifi/setting/__init__.py
pulumiverse_unifi/setting/_inputs.py
pulumiverse_unifi/setting/mgmt.py
pulumiverse_unifi/setting/outputs.py
pulumiverse_unifi/setting/radius.py
pulumiverse_unifi/setting/usg.py
pulumiverse_unifi-0.1.1.dist-info/METADATA
pulumiverse_unifi-0.1.1.dist-info/WHEEL
pulumiverse_unifi-0.1.1.dist-info/top_level.txt
pulumiverse_unifi-0.1.1.dist-info/RECORD
