Metadata-Version: 2.1
Name: pulumiverse_unifi
Version: 0.1.1
Summary: A Pulumi package for creating and managing Unifi network resources.
License: Apache-2.0
Project-URL: Homepage, https://github.com/pulumiverse
Project-URL: Repository, https://github.com/pulumiverse/pulumi-unifi
Keywords: pulumi,unifi,category/network
Requires-Python: >=3.8
Requires-Dist: parver>=0.2.1
Requires-Dist: pulumi<4.0.0,>=3.0.0
Requires-Dist: semver>=2.8.1
